LICENSE
MANIFEST.in
README.md
setup.cfg
setup.py
dfparser/__init__.py
dfparser/envelope_parser.py
dfparser/requirements.txt
dfparser/rsb_event_pb2.py
dfparser/rsh_parser.py
dfparser.egg-info/PKG-INFO
dfparser.egg-info/SOURCES.txt
dfparser.egg-info/dependency_links.txt
dfparser.egg-info/requires.txt
dfparser.egg-info/top_level.txt
dfparser/configs/__init__.py
dfparser/configs/rsb_event.proto
dfparser/df_data/__init__.py
dfparser/df_data/def_values.py
dfparser/df_data/type_codes.py