Metadata-Version: 1.0
Name: dfparser
Version: 0.0.20
Summary: Parser for dataforge-envelope (http://npm.mipt.ru/dataforge/) format.
Home-page: https://github.com/kapot65/python-df-parser
Author: Vasilii Chernov
Author-email: kapot65@gmail.com
License: UNKNOWN
Keywords: dataforge,parser
Platform: any
